[
  {
    "id": "402741533095",
    "position": 0,
    "title": "6.82'' M11 PRO Android 10.1 Smart Phone 8GB+128GB 10 Core Dual SIM Card Unlocked",
    "price": "ILS 229.12 to ILS 232.06",
    "shippingPrice": "+ILS 34.91 shipping",
    "shippingCountry": "China",
    "sponsored": true,
    "imageUrl": "https://i.ebayimg.com/thumbs/images/g/xdwAAOSwrYZgZI-Z/s-l225.jpg"
  },
  {
    "id": "114711167770",
    "position": 1,
    "title": "Apple iPhone 8 Plus 64GB 256GB - Factory Unlocked AT&T Verizon T-Mobile",
    "price": "ILS 746.96 to ILS 1,006.78",
    "shippingPrice": "+ILS 86.98 shipping estimate",
    "shippingCountry": "United States",
    "sponsored": true,
    "imageUrl": "https://i.ebayimg.com/thumbs/images/g/BnIAAOSw3iFeHLkU/s-l225.jpg"
  },
  {
    "id": "113652223677",
    "position": 2,
    "title": "Apple iPhone 8 - 64GB/256GB - Gold/Grey/ Silver - UNLOCKED - Various Grades",
    "price": "ILS 596.27 to ILS 1,009.10",
    "shippingPrice": "+ILS 91.24 shipping estimate",
    "shippingCountry": "United Kingdom",
    "sponsored": true,
    "imageUrl": "https://i.ebayimg.com/thumbs/images/g/3QcAAOSw04ZcaxXH/s-l225.jpg"
  },
  {
    "id": "143966345913",
    "position": 3,
    "title": "Apple iPhone 8 64GB Factory Unlocked Smartphone",
    "price": "ILS 535.85",
    "shippingPrice": "+ILS 80.77 shipping estimate",
    "shippingCountry": "United States",
    "sponsored": true,
    "imageUrl": "https://i.ebayimg.com/thumbs/images/g/LLkAAOSwpUlgEbZo/s-l225.jpg"
  },
  {
    "id": "363296604619",
    "position": 4,
    "title": "Google - Pixel 3 with 64GB Memory Cell Phone (Unlocked) - Not Pink - New SEALED",
    "price": "ILS 516.40",
    "shippingPrice": "+ILS 97.27 shipping",
    "shippingCountry": "United States",
    "sponsored": false,
    "imageUrl": "https://i.ebayimg.com/thumbs/images/g/CGYAAOSw7YRgSlqH/s-l225.jpg"
  },
  {
    "id": "184310543299",
    "position": 5,
    "title": "Samsung Galaxy Note10+  Plus SM-N975U1 - 256GB White Black Glow (Unlocked) A",
    "price": "ILS 1,266.61",
    "shippingPrice": "+ILS 90.78 shipping estimate",
    "shippingCountry": "United States",
    "sponsored": true,
    "imageUrl": "https://i.ebayimg.com/thumbs/images/g/NvMAAOSwe4hdu3eB/s-l225.jpg"
  },
  {
    "id": "383853973992",
    "position": 6,
    "title": "Brand New LG V60 ThinQ 5G LM-V600AM 128GB Blue GSM AT&T GSM Unlocked Smartphone",
    "price": "ILS 1,266.61",
    "shippingPrice": "+ILS 94.71 shipping estimate",
    "shippingCountry": "United States",
    "sponsored": false,
    "imageUrl": "https://i.ebayimg.com/thumbs/images/g/vvAAAOSwZW5f1AHU/s-l225.jpg"
  },
  {
    "id": "303279232871",
    "position": 7,
    "title": "Apple iPhone X Smartphone 64GB 256GB AT&T Sprint T-Mobile Verizon or Unlocked",
    "price": "ILS 841.18 to ILS 1,117.24",
    "shippingPrice": "+ILS 90.32 shipping estimate",
    "shippingCountry": "United States",
    "sponsored": false,
    "imageUrl": "https://i.ebayimg.com/thumbs/images/g/oCIAAOSwpdhgirog/s-l225.jpg"
  },
  {
    "id": "265160341875",
    "position": 8,
    "title": "Samsung Galaxy S9 SM-G960F 64GB Unlocked Smart Phone SIM FREE UK SELLER FAIR CON",
    "price": "ILS 591.68",
    "shippingPrice": "+ILS 86.97 shipping estimate",
    "shippingCountry": "United Kingdom",
    "sponsored": false,
    "imageUrl": "https://i.ebayimg.com/thumbs/images/g/s0YAAOSwi~JgRVuk/s-l225.jpg"
  },
  {
    "id": "333926110650",
    "position": 9,
    "title": "Samsung Galaxy S10+ Plus G975 GSM Unlocked Straight Talk T-Mobile AT&T Verizon",
    "price": "ILS 925.59 to ILS 1,006.78",
    "shippingPrice": "+ILS 89.77 shipping estimate",
    "shippingCountry": "United States",
    "sponsored": false,
    "imageUrl": "https://i.ebayimg.com/thumbs/images/g/jEUAAOSw~RZgVJ0T/s-l225.jpg"
  },
  {
    "id": "274505797468",
    "position": 10,
    "title": "Apple iPhone 8 64GB Factory Unlocked Verizon AT&T T-Mobile Sprint",
    "price": "ILS 613.83",
    "shippingPrice": "+ILS 82.23 shipping estimate",
    "shippingCountry": "United States",
    "sponsored": false,
    "imageUrl": "https://i.ebayimg.com/thumbs/images/g/Yc8AAOSwJstgQBmR/s-l225.jpg"
  },
  {
    "id": "293463314986",
    "position": 11,
    "title": "Apple iPhone 11 Pro Smartphone AT&T Sprint T-Mobile Verizon or Unlocked LTE",
    "price": "ILS 1,685.61 to ILS 2,302.69",
    "shippingPrice": "+ILS 103.96 shipping estimate",
    "shippingCountry": "United States",
    "sponsored": false,
    "imageUrl": "https://i.ebayimg.com/thumbs/images/g/8DEAAOSw3rtgirp4/s-l225.jpg"
  },
  {
    "id": "284309185669",
    "position": 12,
    "title": "New ListingApple iPhone 11 - 64GB - Purple (Verizon) A2111 (CDMA + GSM)",
    "price": "ILS 798.83",
    "shippingPrice": "Free International Shipping",
    "shippingCountry": "Malaysia",
    "sponsored": false,
    "imageUrl": "https://i.ebayimg.com/thumbs/images/g/xvwAAOSwSKBeNsl4/s-l225.jpg"
  },
  {
    "id": "265175017736",
    "position": 13,
    "title": "New ListingmPTech Hammer 4+ Rugged Mobile Phone Silver",
    "price": "ILS 183.48",
    "shippingPrice": "+ILS 152.20 shipping estimate",
    "shippingCountry": "United Kingdom",
    "sponsored": false,
    "imageUrl": "https://i.ebayimg.com/thumbs/images/g/SzUAAOSwtGdgnlUe/s-l225.jpg"
  },
  {
    "id": "302847614914",
    "position": 14,
    "title": "Apple iPhone 8 Plus Smartphone AT&T Sprint T-Mobile Verizon or Unlocked 4G LTE",
    "price": "ILS 714.52 to ILS 1,019.81",
    "shippingPrice": "+ILS 86.29 shipping estimate",
    "shippingCountry": "United States",
    "sponsored": true,
    "imageUrl": "https://i.ebayimg.com/thumbs/images/g/T-MAAOSw1QlgirnG/s-l225.jpg"
  },
  {
    "id": "174316316884",
    "position": 15,
    "title": "Samsung Galaxy S10 Plus SM-G975U1 - 128GB AT&T Verizon T-mobile (Unlocked) A ",
    "price": "ILS 974.31",
    "shippingPrice": "+ILS 89.12 shipping estimate",
    "shippingCountry": "United States",
    "sponsored": true,
    "imageUrl": "https://i.ebayimg.com/thumbs/images/g/r8MAAOSwcpte4acu/s-l225.jpg"
  },
  {
    "id": "174105091978",
    "position": 16,
    "title": "Apple iPhone X | 64GB 256GB | Unlocked Verizon AT&T T-Mobile Sprint | CDMA/GSM",
    "price": "ILS 1,022.99 to ILS 1,428.97",
    "shippingPrice": "+ILS 95.97 shipping estimate",
    "shippingCountry": "United States",
    "sponsored": true,
    "imageUrl": "https://i.ebayimg.com/thumbs/images/g/VfMAAOSwDoNd2W90/s-l225.jpg"
  },
  {
    "id": "373499672299",
    "position": 17,
    "title": "Apple iPhone 8 64GB LTE Factory Unlocked Smartphone - Space Gray ",
    "price": "ILS 519.62",
    "shippingPrice": "+ILS 80.45 shipping estimate",
    "shippingCountry": "United States",
    "sponsored": true,
    "imageUrl": "https://i.ebayimg.com/thumbs/images/g/A8QAAOSwVA5aFXY4/s-l225.jpg"
  },
  {
    "id": "174783348636",
    "position": 18,
    "title": "New Listing5.5“ HOMTOM HT80 Waterproof Smartphone 4G Android Rugged NFC Wireless Charging",
    "price": "ILS 366.92",
    "shippingPrice": "Free International Shipping",
    "shippingCountry": "China",
    "sponsored": false,
    "imageUrl": "https://i.ebayimg.com/thumbs/images/g/qAAAAOSwpzNgbdfu/s-l225.jpg"
  },
  {
    "id": "333709835862",
    "position": 19,
    "title": "Apple iPhone X Unlocked Smartphone 📱 64GB 256GB Verizon T-Mobile AT&T GSM CDMA",
    "price": "ILS 958.07 to ILS 1,104.22",
    "shippingPrice": "+ILS 97.08 shipping",
    "shippingCountry": "United States",
    "sponsored": false,
    "imageUrl": "https://i.ebayimg.com/thumbs/images/g/WfgAAOSwqWtglDkF/s-l225.jpg"
  },
  {
    "id": "124676902137",
    "position": 20,
    "title": "SAMSUNG Galaxy A12 2021 128GB Mobile Smart Phone Unlocked Black Blue White Red",
    "price": "ILS 562.09 to ILS 697.18",
    "shippingPrice": "+ILS 88.90 shipping estimate",
    "shippingCountry": "United Kingdom",
    "sponsored": false,
    "imageUrl": "https://i.ebayimg.com/thumbs/images/g/33kAAOSwnatgEJGU/s-l225.jpg"
  },
  {
    "id": "284309172821",
    "position": 21,
    "title": "New ListingApple iPhone 7 128GB A1778 (GSM) (Unlocked) -",
    "price": "ILS 366.96",
    "shippingPrice": "+ILS 135.32 shipping estimate",
    "shippingCountry": "United Kingdom",
    "sponsored": false,
    "imageUrl": "https://i.ebayimg.com/thumbs/images/g/K3YAAOSwNPFgp9qH/s-l225.jpg"
  },
  {
    "id": "353183423603",
    "position": 22,
    "title": "Apple iPhone SE 2nd Gen (2020) 🍎 64GB 128GB 256GB 📱 Fully Unlocked Smartphone",
    "price": "ILS 811.92 to ILS 1,152.94",
    "shippingPrice": "+ILS 97.08 shipping",
    "shippingCountry": "United States",
    "sponsored": false,
    "imageUrl": "https://i.ebayimg.com/thumbs/images/g/sboAAOSw4O9ghvLJ/s-l225.jpg"
  },
  {
    "id": "383936740393",
    "position": 23,
    "title": "New LG Velvet 4G & 5G LMG900UM1 128GB Aurora Silver (AT&T+ GSM Unlocked) Phone",
    "price": "ILS 909.35",
    "shippingPrice": "+ILS 87.89 shipping estimate",
    "shippingCountry": "United States",
    "sponsored": false,
    "imageUrl": "https://i.ebayimg.com/thumbs/images/g/GTAAAOSwQ-NgHEkY/s-l225.jpg"
  },
  {
    "id": "333565033763",
    "position": 24,
    "title": "Unlocked Apple iPhone 11 Pro 🍎 64GB 256GB 512GB T-Mobile ATT Verizon Smartphone",
    "price": "ILS 1,786.26 to ILS 2,221.46",
    "shippingPrice": "+ILS 97.08 shipping",
    "shippingCountry": "United States",
    "sponsored": false,
    "imageUrl": "https://i.ebayimg.com/thumbs/images/g/Mt4AAOSwq~xgoqdo/s-l225.jpg"
  },
  {
    "id": "193302493134",
    "position": 25,
    "title": "NEW UNLOCKED Samsung Galaxy S10 SM-G973U 128GB BLACK S10 GSM T-MOBILE AT&T",
    "price": "ILS 1,250.01",
    "shippingPrice": "+ILS 94.41 shipping estimate",
    "shippingCountry": "United States",
    "sponsored": false,
    "imageUrl": "https://i.ebayimg.com/thumbs/images/g/-nUAAOSwLfxeH-lO/s-l225.jpg"
  },
  {
    "id": "164885986811",
    "position": 26,
    "title": "New ListingApple iPhone 11 (PRODUCT) RED 64GB (Unlocked) Excellent Condition",
    "price": "ILS 233.94",
    "shippingPrice": "+ILS 146.23 shipping estimate",
    "shippingCountry": "United Kingdom",
    "sponsored": false,
    "imageUrl": "https://i.ebayimg.com/thumbs/images/g/V1UAAOSwm~lgr1j0/s-l225.jpg"
  },
  {
    "id": "313533386562",
    "position": 27,
    "title": "Samsung Galaxy S8 Active SM-G892A - 64GB - Gray (GSM Unlocked) Smartphone harsha",
    "price": "ILS 324.35",
    "shippingPrice": "Free International Shipping",
    "shippingCountry": "Sri Lanka",
    "sponsored": false,
    "imageUrl": "https://i.ebayimg.com/thumbs/images/g/magAAOSwDttgo5BU/s-l225.jpg"
  },
  {
    "id": "234003545676",
    "position": 28,
    "title": "Sonim XP8 XP8800 64GB - Black (Unlocked) Smartphone (Dual SIM)-BRAND NEW IN BOX",
    "price": "ILS 649.53",
    "shippingPrice": "+ILS 82.92 shipping estimate",
    "shippingCountry": "United States",
    "sponsored": false,
    "imageUrl": "https://i.ebayimg.com/thumbs/images/g/nYgAAOSwVEVgEaTC/s-l225.jpg"
  },
  {
    "id": "264854434421",
    "position": 29,
    "title": "Google Pixel 3a 3a XL 3 3 XL 64GB / 128GB T-Mobile OR GSM Unlocked Smartphone",
    "price": "ILS 246.70 to ILS 458.98",
    "shippingPrice": "+ILS 194.71 shipping",
    "shippingCountry": "United States",
    "sponsored": false,
    "imageUrl": "https://i.ebayimg.com/thumbs/images/g/sp4AAOSw3fNgW0ib/s-l225.jpg"
  },
  {
    "id": "254965476516",
    "position": 30,
    "title": "Samsung Galaxy S20 5G G981U1 Gray AT&T T-Mobile Sprint Verizon Factory Unlocked",
    "price": "ILS 1,506.98 to ILS 1,620.65",
    "shippingPrice": "+ILS 99.32 shipping estimate",
    "shippingCountry": "United States",
    "sponsored": false,
    "imageUrl": "https://i.ebayimg.com/thumbs/images/g/1XkAAOSw9TlgkE6z/s-l225.jpg"
  },
  {
    "id": "194060416913",
    "position": 31,
    "title": "Xiaomi Redmi Note 10 Pro 128GB 6GB RAM (FACTORY UNLOCKED) 6.67\" 108MP (Global)",
    "price": "ILS 1,165.76",
    "shippingPrice": "+ILS 116.89 shipping",
    "shippingCountry": "United States",
    "sponsored": false,
    "imageUrl": "https://i.ebayimg.com/thumbs/images/g/4nAAAOSwfmBgR9-L/s-l225.jpg"
  },
  {
    "id": "164886005243",
    "position": 32,
    "title": "New ListingApple iPhone 11 Pro Max - 256GB - Space Grey (Unlocked)",
    "price": "ILS 1,421.98",
    "shippingPrice": "+ILS 136.19 shipping estimate",
    "shippingCountry": "United Kingdom",
    "sponsored": false,
    "imageUrl": "https://i.ebayimg.com/thumbs/images/g/r9AAAOSwLZJgr2D7/s-l225.jpg"
  },
  {
    "id": "254398277923",
    "position": 33,
    "title": "Samsung Galaxy Note 9 N960U 128/512 ATT T-Mobile Sprint Verizon Carrier Unlocked",
    "price": "ILS 799.12 to ILS 1,107.66",
    "shippingPrice": "+ILS 89.61 shipping estimate",
    "shippingCountry": "United States",
    "sponsored": false,
    "imageUrl": "https://i.ebayimg.com/thumbs/images/g/yZEAAOSwJWFgR~7k/s-l225.jpg"
  },
  {
    "id": "264838995856",
    "position": 34,
    "title": "Razer Phone 1 / 2 RZ35-0215/0259 64GB AT&T OR GSM Unlocked Gaming Smartphone ",
    "price": "ILS 538.19 to ILS 828.06",
    "shippingPrice": "+ILS 194.71 shipping",
    "shippingCountry": "United States",
    "sponsored": false,
    "imageUrl": "https://i.ebayimg.com/thumbs/images/g/j~IAAOSwND9gWe0C/s-l225.jpg"
  },
  {
    "id": "254628167761",
    "position": 35,
    "title": "NEW Samsung Galaxy S10e G970U 128 Sprint AT&T T-Mobile Verizon Factory Unlocked",
    "price": "ILS 808.70 to ILS 1,068.53",
    "shippingPrice": "+ILS 88.44 shipping estimate",
    "shippingCountry": "United States",
    "sponsored": false,
    "imageUrl": "https://i.ebayimg.com/thumbs/images/g/MA0AAOSw0mRgkBqN/s-l225.jpg"
  },
  {
    "id": "254949537885",
    "position": 36,
    "title": "NEW Samsung Galaxy S10 Black 128GB Sprint AT&T T-Mobile Verizon Factory Unlocked",
    "price": "ILS 936.34 to ILS 1,133.48",
    "shippingPrice": "+ILS 92.17 shipping estimate",
    "shippingCountry": "United States",
    "sponsored": false,
    "imageUrl": "https://i.ebayimg.com/thumbs/images/g/hUEAAOSw3jBggcHY/s-l225.jpg"
  },
  {
    "id": "284309104618",
    "position": 37,
    "title": "New ListingApple iPhone 8 - 64GB - Gold (Unlocked) A1905 (GSM)",
    "price": "ILS 343.11",
    "shippingPrice": "Free International Shipping",
    "shippingCountry": "United States",
    "sponsored": false,
    "imageUrl": "https://i.ebayimg.com/thumbs/images/g/0RAAAOSw-hBgr1n6/s-l225.jpg"
  },
  {
    "id": "303476035378",
    "position": 38,
    "title": "Apple iPhone 11 Smartphone 64GB 128GB AT&T Sprint T-Mobile Verizon or Unlocked",
    "price": "ILS 1,393.30 to ILS 1,783.04",
    "shippingPrice": "+ILS 100.84 shipping estimate",
    "shippingCountry": "United States",
    "sponsored": true,
    "imageUrl": "https://i.ebayimg.com/thumbs/images/g/EnoAAOSwsthgirqR/s-l225.jpg"
  },
  {
    "id": "393049362798",
    "position": 39,
    "title": "Original Motorola RAZR V3 Flip Mobile Phone Unlocked Cellphone Camera  2G GSM",
    "price": "ILS 86.36",
    "shippingPrice": "+ILS 25.95 shipping",
    "shippingCountry": "China",
    "sponsored": true,
    "imageUrl": "https://i.ebayimg.com/thumbs/images/g/NLcAAOSwzkpgjCjt/s-l225.jpg"
  },
  {
    "id": "273923904793",
    "position": 40,
    "title": "NEW LG G7 ThinQ G710AWM 64GB 4G LTE Factory GSM Unlocked Smartphone",
    "price": "ILS 487.14",
    "shippingPrice": "+ILS 79.83 shipping estimate",
    "shippingCountry": "United States",
    "sponsored": false,
    "imageUrl": "https://i.ebayimg.com/thumbs/images/g/J9QAAOSwKeNd1HQj/s-l225.jpg"
  },
  {
    "id": "124640555584",
    "position": 41,
    "title": "Google Pixel 4 - 64GB - White Factory Unlocked LTE Smartphone - Open Box",
    "price": "ILS 811.92",
    "shippingPrice": "+ILS 86.03 shipping estimate",
    "shippingCountry": "United States",
    "sponsored": false,
    "imageUrl": "https://i.ebayimg.com/thumbs/images/g/EMMAAOSwuZZgR~2u/s-l225.jpg"
  },
  {
    "id": "144053864028",
    "position": 42,
    "title": "New ListingNOKIA 1 TA-160 8GB SMARTPHONE DARK BLUE 02 /TESCOS  #4",
    "price": "ILS 22.89",
    "shippingPrice": "+ILS 138.39 shipping estimate",
    "shippingCountry": "United Kingdom",
    "sponsored": false,
    "imageUrl": "https://i.ebayimg.com/thumbs/images/g/CesAAOSwMihgo5BV/s-l225.jpg"
  },
  {
    "id": "224294284117",
    "position": 43,
    "title": "Realme 7 Pro 128GB 8GB RAM RMX2170 (FACTORY UNLOCKED) 6.4\" 64MP (Global)",
    "price": "ILS 941.83",
    "shippingPrice": "+ILS 116.89 shipping",
    "shippingCountry": "United States",
    "sponsored": false,
    "imageUrl": "https://i.ebayimg.com/thumbs/images/g/-igAAOSw~O5gUimj/s-l225.jpg"
  },
  {
    "id": "283848914884",
    "position": 44,
    "title": "Apple iPhone XR 64/128/256GB A1984 A2105 AT&T T-Mobile Verizon Xfinity Unlocked",
    "price": "ILS 990.55 to ILS 1,104.22",
    "shippingPrice": "+ILS 90.39 shipping estimate",
    "shippingCountry": "United States",
    "sponsored": false,
    "imageUrl": "https://i.ebayimg.com/thumbs/images/g/4AkAAOSwvAJfQEPm/s-l225.jpg"
  },
  {
    "id": "193649286833",
    "position": 45,
    "title": "LG V50 ThinQ 128GB Black (Sprint) Worldwide GSM Unlocked New Open Box Read Note",
    "price": "ILS 844.39",
    "shippingPrice": "+ILS 86.65 shipping estimate",
    "shippingCountry": "United States",
    "sponsored": false,
    "imageUrl": "https://i.ebayimg.com/thumbs/images/g/P3gAAOSwehZfUrzj/s-l225.jpg"
  },
  {
    "id": "274790367491",
    "position": 46,
    "title": "OnePlus 7T 128GB Glacier Blue Unlocked - NEW & SEALED",
    "price": "ILS 1,094.48",
    "shippingPrice": "+ILS 91.43 shipping estimate",
    "shippingCountry": "United States",
    "sponsored": false,
    "imageUrl": "https://i.ebayimg.com/thumbs/images/g/4hcAAOSwuP1glrTv/s-l225.jpg"
  },
  {
    "id": "254958258986",
    "position": 47,
    "title": "Samsung Galaxy S20 Ultra 5G G988U1 AT&T T-Mobile Sprint Verizon Factory Unlocked",
    "price": "ILS 1,994.15 to ILS 2,124.06",
    "shippingPrice": "+ILS 109.22 shipping estimate",
    "shippingCountry": "United States",
    "sponsored": false,
    "imageUrl": "https://i.ebayimg.com/thumbs/images/g/eFMAAOSwDV1giHnE/s-l225.jpg"
  },
  {
    "id": "144053919531",
    "position": 48,
    "title": "New ListingAPPLE IPHONE 7 Black 32GB - UNLOCKED - Superb Condition - Boxed",
    "price": "ILS 458.70",
    "shippingPrice": "+ILS 105.50 shipping",
    "shippingCountry": "United Kingdom",
    "sponsored": false,
    "imageUrl": "https://i.ebayimg.com/thumbs/images/g/wNUAAOSwVURgr3D9/s-l225.jpg"
  },
  {
    "id": "373592599386",
    "position": 49,
    "title": "New ListingApple iPhone 12 Pro MAX 512GB Pacific Blue Unlocked",
    "price": "ILS 1,605.80",
    "shippingPrice": "+ILS 13.40 shipping",
    "shippingCountry": "Malaysia",
    "sponsored": false,
    "imageUrl": "https://i.ebayimg.com/thumbs/images/g/-s4AAOSwdcBgrYVQ/s-l225.jpg"
  },
  {
    "id": "223986366341",
    "position": 50,
    "title": "Apple iPhone 8 - 64GB - 256GB - Unlocked - Smartphone - SIM Free - All Colours",
    "price": "ILS 550.21 to ILS 963.05",
    "shippingPrice": "+ILS 90.41 shipping estimate",
    "shippingCountry": "United Kingdom",
    "sponsored": false,
    "imageUrl": "https://i.ebayimg.com/thumbs/images/g/xCoAAOSwm2pf~NV0/s-l225.jpg"
  },
  {
    "id": "223646303020",
    "position": 51,
    "title": "APPLE iPHONE 6 PLUS 16GB / 64GB / 128GB - Unlocked - Smartphone Mobile Phone ",
    "price": "ILS 408.25 to ILS 545.86",
    "shippingPrice": "+ILS 183.25 shipping",
    "shippingCountry": "United Kingdom",
    "sponsored": false,
    "imageUrl": "https://i.ebayimg.com/thumbs/images/g/hJQAAOSw9zxeJy9u/s-l225.jpg"
  },
  {
    "id": "194131895884",
    "position": 52,
    "title": "Google Pixel 4 XL 64GB - Just Black White Orange Unlocked (Single SIM) A Stock",
    "price": "ILS 844.39",
    "shippingPrice": "+ILS 86.65 shipping estimate",
    "shippingCountry": "United States",
    "sponsored": false,
    "imageUrl": "https://i.ebayimg.com/thumbs/images/g/VYwAAOSw9ehgoFVy/s-l225.jpg"
  },
  {
    "id": "233533129675",
    "position": 53,
    "title": "Unlocked Apple iPhone 11 🍎 64GB 128GB 256GB Verizon T-Mobile AT&T 📱 Smartphone",
    "price": "ILS 1,461.48 to ILS 1,883.69",
    "shippingPrice": "+ILS 97.08 shipping",
    "shippingCountry": "United States",
    "sponsored": false,
    "imageUrl": "https://i.ebayimg.com/thumbs/images/g/pssAAOSwXOBgiBrA/s-l225.jpg"
  },
  {
    "id": "233999899750",
    "position": 54,
    "title": "Google Pixel 4 🧚 64GB 128GB Verizon T-Mobile AT&T GSM CDMA Unlocked Smartphone",
    "price": "ILS 714.48",
    "shippingPrice": "+ILS 97.08 shipping",
    "shippingCountry": "United States",
    "sponsored": false,
    "imageUrl": "https://i.ebayimg.com/thumbs/images/g/C9kAAOSwv6xglapZ/s-l225.jpg"
  },
  {
    "id": "313450991511",
    "position": 55,
    "title": "Huawei P30 Pro 128GB VOG-L09 Unlocked  4G Android Smartphone Excellent Device",
    "price": "ILS 917.36 to ILS 1,146.71",
    "shippingPrice": "+ILS 92.89 shipping estimate",
    "shippingCountry": "United Kingdom",
    "sponsored": false,
    "imageUrl": "https://i.ebayimg.com/thumbs/images/g/4UQAAOSwYjdgSlQp/s-l225.jpg"
  },
  {
    "id": "293240550620",
    "position": 56,
    "title": "Samsung Galaxy S10 Smartphone AT&T Sprint T-Mobile Verizon or Unlocked",
    "price": "ILS 711.27 to ILS 922.37",
    "shippingPrice": "+ILS 90.16 shipping estimate",
    "shippingCountry": "United States",
    "sponsored": false,
    "imageUrl": "https://i.ebayimg.com/thumbs/images/g/UWkAAOSwEpJdhSB-/s-l225.jpg"
  },
  {
    "id": "352847954931",
    "position": 57,
    "title": "Apple iPhone XS Unlocked 🍎 64GB 256GB 512GB Verizon T-Mobile AT&T Smartphone",
    "price": "ILS 1,023.02",
    "shippingPrice": "+ILS 97.08 shipping",
    "shippingCountry": "United States",
    "sponsored": false,
    "imageUrl": "https://i.ebayimg.com/thumbs/images/g/T7EAAOSwa5dgZH7H/s-l225.jpg"
  },
  {
    "id": "114749370742",
    "position": 58,
    "title": "Apple iPhone 8 64GB GSM Factory Unlocked Smartphone",
    "price": "ILS 503.38",
    "shippingPrice": "+ILS 81.19 shipping",
    "shippingCountry": "United States",
    "sponsored": false,
    "imageUrl": "https://i.ebayimg.com/thumbs/images/g/n2EAAOSwq7RgZesb/s-l225.jpg"
  },
  {
    "id": "222827843368",
    "position": 59,
    "title": "APPLE iPHONE SE 1st Gen - 16GB / 64GB / 128GB -  Unlocked - Smartphone Mobile ",
    "price": "ILS 307.33 to ILS 435.77",
    "shippingPrice": "Shipping not specified",
    "shippingCountry": "United Kingdom",
    "sponsored": false,
    "imageUrl": "https://i.ebayimg.com/thumbs/images/g/wqQAAOSwoDVeJ0iN/s-l225.jpg"
  },
  {
    "id": "174770265619",
    "position": 60,
    "title": "Google Pixel 4 64GB - Just Black White Orange Unlocked (Single SIM) B Stock",
    "price": "ILS 616.76 to ILS 617.05",
    "shippingPrice": "+ILS 82.30 shipping estimate",
    "shippingCountry": "United States",
    "sponsored": false,
    "imageUrl": "https://i.ebayimg.com/thumbs/images/g/VYwAAOSw9ehgoFVy/s-l225.jpg"
  },
  {
    "id": "254914702412",
    "position": 61,
    "title": "Mini Mobile Cell Phone L8STAR BM10 Pocket Tiny GSM Dual SIM Bluetooth Children",
    "price": "ILS 22.89 to ILS 41.24",
    "shippingPrice": "Free International Shipping",
    "shippingCountry": "China",
    "sponsored": true,
    "imageUrl": "https://i.ebayimg.com/thumbs/images/g/SJ0AAOSwMapgWv~I/s-l225.jpg"
  },
  {
    "id": "174110785206",
    "position": 62,
    "title": "Apple iPhone XR Smartphone | 64GB 128GB 256GB | Unlocked Verizon AT&T T-Mobile",
    "price": "ILS 1,055.47 to ILS 1,656.31",
    "shippingPrice": "+ILS 92.04 shipping estimate",
    "shippingCountry": "United States",
    "sponsored": true,
    "imageUrl": "https://i.ebayimg.com/thumbs/images/g/2ZUAAOSw4pJd2XZh/s-l225.jpg"
  }
]
